datarobot_mlops/agent.py
datarobot_mlops/constants.py
datarobot_mlops/event.py
datarobot_mlops/json_shim.py
datarobot_mlops/metric.py
datarobot_mlops/mlops.py
datarobot_mlops/model.py
datarobot_mlops/channel/__init__.py
datarobot_mlops/channel/output_channel_queue.py
datarobot_mlops/channel/record.py
datarobot_mlops/common/__init__.py
datarobot_mlops/common/api_sync.py
datarobot_mlops/common/config.py
datarobot_mlops/common/connected_exception.py
datarobot_mlops/common/datarobot_url_helper.py
datarobot_mlops/common/enums.py
datarobot_mlops/common/exception.py
datarobot_mlops/common/prediction_util.py
datarobot_mlops/common/reporting_api_client.py
datarobot_mlops/common/sampling.py
datarobot_mlops/common/sanitize.py
datarobot_mlops/common/singleton.py
datarobot_mlops/common/stringutil.py
datarobot_mlops/common/version_util.py
datarobot_mlops/spooler/__init__.py
datarobot_mlops/spooler/api_spooler.py
datarobot_mlops/spooler/async_memory_spooler.py
datarobot_mlops/spooler/filesystem_spooler.py
datarobot_mlops/spooler/kafka_spooler.py
datarobot_mlops/spooler/memory_spooler.py
datarobot_mlops/spooler/pubsub_spooler.py
datarobot_mlops/spooler/rabbitmq_spooler.py
datarobot_mlops/spooler/record_spooler.py
datarobot_mlops/spooler/record_spooler_factory.py
datarobot_mlops/spooler/spooler_offset_manager.py
datarobot_mlops/spooler/sqs_spool.py
datarobot_mlops/spooler/stdout_spooler.py
datarobot_mlops-11.1.0.data/data/share/mlops/agent.yaml
datarobot_mlops-11.1.0.data/data/share/mlops/mlops.log4j2.properties
datarobot_mlops-11.1.0.dist-info/METADATA
datarobot_mlops-11.1.0.dist-info/WHEEL
datarobot_mlops-11.1.0.dist-info/top_level.txt
datarobot_mlops-11.1.0.dist-info/RECORD
