Metadata-Version: 2.1
Name: datarobot-mlops
Version: 11.1.0
Summary: datarobot-mlops library to read and report MLOps statistics
Home-page: http://datarobot.com
Author: DataRobot
Author-email: support@datarobot.com
Maintainer: DataRobot
Maintainer-email: info@datarobot.com
License: DataRobot Tool and Utility Agreement
Project-URL: Documentation, https://docs.datarobot.com/en/docs/mlops/deployment/mlops-agent/spooler.html#mlops-library-configuration
Platform: UNKNOWN
Classifier: Programming Language :: Python :: 3
Classifier: Programming Language :: Python :: 3.9
Classifier: Programming Language :: Python :: 3.10
Classifier: License :: Other/Proprietary License
Classifier: Operating System :: MacOS
Classifier: Operating System :: POSIX
Classifier: Operating System :: Unix
Requires-Python: >=3.9
Requires-Dist: python-dateutil
Requires-Dist: pandas (>=0.20)
Requires-Dist: pyyaml
Requires-Dist: py4j (>=0.10.9.1)
Requires-Dist: orjson (>=3)
Provides-Extra: aggregator
Requires-Dist: datarobot-mlops-stats-aggregator (>=10.2.3) ; extra == 'aggregator'
Provides-Extra: api
Requires-Dist: requests (>=2.32) ; extra == 'api'
Provides-Extra: aws
Requires-Dist: boto3 (>=1.11.4) ; extra == 'aws'
Provides-Extra: azure
Requires-Dist: azure-identity (>=1.0) ; extra == 'azure'
Provides-Extra: google
Requires-Dist: google-cloud-pubsub (>=2) ; extra == 'google'
Provides-Extra: kafka
Requires-Dist: confluent-kafka (!=2.6.0,>=1.5.0) ; extra == 'kafka'
Requires-Dist: certifi ; extra == 'kafka'
Provides-Extra: rabbitmq
Requires-Dist: pika (>=1.0) ; extra == 'rabbitmq'
